<?xml version="1.0" encoding="UTF-8"?>
<Configuration>
    <Appenders>
        <Console name="Console" target="SYSTEM_OUT">
            <PatternLayout>
                <ScriptPatternSelector defaultPattern="">
                    <Script name="LevelSelector" language="javascript"><![CDATA[

                    // https://logging.apache.org/log4j/2.x/manual/configuration.html

                            result=null;
                            switch (logEvent.getLevel())
                            {
                                case org.apache.logging.log4j.Level.DEBUG:
                                case org.apache.logging.log4j.Level.INFO:result=logEvent.getLevel();
                                                                         break;
                                default:result=null;
                            }
                            result;
                            ]]>
                    </Script>
                    <PatternMatch key="DEBUG" pattern="[%-5level] %d{yyyy-MM-dd HH:mm:ss.SSS} %l - %msg%n"/>
                    <PatternMatch key="INFO" pattern="%d{yyyy-MM-dd HH:mm:ss.SSS} %msg%n"/>
                </ScriptPatternSelector>
            </PatternLayout>
        </Console>
    </Appenders>
    <Loggers>
        <Root level="trace">
            <AppenderRef ref="Console"/>
        </Root>
    </Loggers>
</Configuration>
